Workbook

Sheet Start Here
A1: Max_imum Designs: Business Tracker
A2: One workbook for projects, hours, payments, client data and profit per job. Prices come from the 2026/27 rate card.
A4: How to use
A5: 1 | B5: Add each new job on the Projects sheet (blue cells are for you to type). Give every job a short ID such as P001.
A6: 2 | B6: Log every work session on Time Log (date, project ID, task, hours).
A7: 3 | B7: Log every M-Pesa or bank payment on Payments (project ID, type, amount, transaction code).
A8: 4 | B8: Projects calculates deposit due, paid, balance, hours and your real hourly rate. Dashboard summarises everything.
A9: 5 | B9: Clients & Data is your Data Protection Act register: what data you hold, why, and when to delete it.
A10: Colours | B10: Blue text = you type here. Black text = formula, do not overwrite. Row marked EXAMPLE is a sample: replace or delete it.
A11: Assumptions | B11: Hours per service on the Pricing sheet are planning estimates by the author, not market data. Replace them with your own tracked hours after 5 to 10 jobs.

Sheet Dashboard
A1: Dashboard
A2: Updates automatically from the other sheets (example row included in the totals until you delete it).
A4: Total quoted (KES) | B4: =SUM(Projects!H5:H154) -> 12500
A5: Total received (KES) | B5: =SUM(Payments!D5:D400) -> 6250
A6: Still owed on active jobs (KES) | B6: =SUMIFS(Projects!K5:K154,Projects!G5:G154,"<>Cancelled") -> 6250
A7: Hours logged | B7: =SUM('Time Log'!D5:D400) -> 2.5
A8: Average real KES per hour | B8: =IF(B7=0,"",SUMIFS(Projects!H5:H154,Projects!L5:L154,">0")/SUMIFS(Projects!L5:L154,Projects!L5:L154,">0")) -> 5000
A9: Target KES per hour | B9: =Pricing!C3 -> 600
A10: Projects in progress | B10: =COUNTIF(Projects!G5:G154,"In progress")+COUNTIF(Projects!G5:G154,"Awaiting feedback") -> 1
A11: Projects delivered or paid | B11: =COUNTIF(Projects!G5:G154,"Delivered")+COUNTIF(Projects!G5:G154,"Paid in full") -> 0
A12: Enquiries not yet won | B12: =COUNTIF(Projects!G5:G154,"Enquiry")+COUNTIF(Projects!G5:G154,"Quoted") -> 0
A13: Contracts missing signature | B13: =COUNTIFS(Projects!A5:A154,"<>",Projects!O5:O154,"<>Yes") -> 0
A14: Portfolio consent still needed | B14: =COUNTIFS(Projects!A5:A154,"<>",Projects!Q5:Q154,"<>Yes") -> 0
A16: Rule of thumb: if Average real KES per hour is below the target, raise prices or cut scope on the next quote.

Sheet Pricing
A1: Pricing and profitability
A2: Target hourly rate is an input. "Meets target?" compares the price to your estimated hours.
A3: Target hourly rate (KES) | C3: 600 | D3: Assumption: set by you. Change it as your skill and demand grow. | H3: KES per USD | I3: 130
A5: Service | B5: Category | C5: Price (KES) | D5: Est. hours | E5: Price per hour (KES) | F5: Meets target? | G5: USD (at rate below)
A6: Logo Starter | B6: Logo | C6: 4500 | D6: 5 | E6: =IF(D6>0,C6/D6,"") -> 900 | F6: =IF(E6="","",IF(E6>=$C$3,"Yes","Below target")) -> Yes | G6: =ROUND(C6/$I$3,0) -> 35
A7: Logo Standard | B7: Logo | C7: 8500 | D7: 9 | E7: =IF(D7>0,C7/D7,"") -> 944.44444 | F7: =IF(E7="","",IF(E7>=$C$3,"Yes","Below target")) -> Yes | G7: =ROUND(C7/$I$3,0) -> 65
A8: Logo Premium | B8: Logo | C8: 15000 | D8: 14 | E8: =IF(D8>0,C8/D8,"") -> 1071.4286 | F8: =IF(E8="","",IF(E8>=$C$3,"Yes","Below target")) -> Yes | G8: =ROUND(C8/$I$3,0) -> 115
A9: Brand Identity Kit | B9: Brand | C9: 20000 | D9: 28 | E9: =IF(D9>0,C9/D9,"") -> 714.28571 | F9: =IF(E9="","",IF(E9>=$C$3,"Yes","Below target")) -> Yes | G9: =ROUND(C9/$I$3,0) -> 154
A10: Full Brand Suite | B10: Brand | C10: 35000 | D10: 50 | E10: =IF(D10>0,C10/D10,"") -> 700 | F10: =IF(E10="","",IF(E10>=$C$3,"Yes","Below target")) -> Yes | G10: =ROUND(C10/$I$3,0) -> 269
A11: Business card | B11: Print | C11: 2000 | D11: 2 | E11: =IF(D11>0,C11/D11,"") -> 1000 | F11: =IF(E11="","",IF(E11>=$C$3,"Yes","Below target")) -> Yes | G11: =ROUND(C11/$I$3,0) -> 15
A12: Flyer / poster | B12: Print | C12: 2000 | D12: 2.5 | E12: =IF(D12>0,C12/D12,"") -> 800 | F12: =IF(E12="","",IF(E12>=$C$3,"Yes","Below target")) -> Yes | G12: =ROUND(C12/$I$3,0) -> 15
A13: Brochure | B13: Print | C13: 4500 | D13: 6 | E13: =IF(D13>0,C13/D13,"") -> 750 | F13: =IF(E13="","",IF(E13>=$C$3,"Yes","Below target")) -> Yes | G13: =ROUND(C13/$I$3,0) -> 35
A14: Menu (1-2 pages) | B14: Print | C14: 3500 | D14: 4 | E14: =IF(D14>0,C14/D14,"") -> 875 | F14: =IF(E14="","",IF(E14>=$C$3,"Yes","Below target")) -> Yes | G14: =ROUND(C14/$I$3,0) -> 27
A15: Catalogue / booklet (8 pp) | B15: Print | C15: 9000 | D15: 12 | E15: =IF(D15>0,C15/D15,"") -> 750 | F15: =IF(E15="","",IF(E15>=$C$3,"Yes","Below target")) -> Yes | G15: =ROUND(C15/$I$3,0) -> 69
A16: Letterhead / invoice / receipt | B16: Print | C16: 1500 | D16: 1.5 | E16: =IF(D16>0,C16/D16,"") -> 1000 | F16: =IF(E16="","",IF(E16>=$C$3,"Yes","Below target")) -> Yes | G16: =ROUND(C16/$I$3,0) -> 12
A17: Certificate | B17: Print | C17: 1800 | D17: 1.5 | E17: =IF(D17>0,C17/D17,"") -> 1200 | F17: =IF(E17="","",IF(E17>=$C$3,"Yes","Below target")) -> Yes | G17: =ROUND(C17/$I$3,0) -> 14
... A35: Retainer Max (per month) | B35: Retainer | C35: 22000 | D35: 30 | E35: =IF(D35>0,C35/D35,"") -> 733.33333 | F35: =IF(E35="","",IF(E35>=$C$3,"Yes","Below target")) -> Yes | G35: =ROUND(C35/$I$3,0) -> 169

Sheet Projects
A1: Projects
A2: Type in the blue columns. Columns J onward calculate automatically.
A4: ID | B4: Client | C4: Project | D4: Service | E4: Start | F4: Due | G4: Status | H4: Quote (KES) | I4: Deposit due (50%) | J4: Paid to date | K4: Balance due | L4: Hours logged | M4: Real KES/hour | N4: Revision rounds used | O4: Contract signed? | P4: Handover cert signed? | Q4: Portfolio consent? | R4: Notes
A5: P000 EXAMPLE | B5: Wanjiru's Bakery | C5: Logo and 5 posts | D5: Logo Standard | E5: 46329 | F5: 46338 | G5: In progress | H5: 12500 | I5: =IF(A5="","",H5*0.5) -> 6250 | J5: =IF(A5="","",SUMIFS(Payments!$D$5:$D$2000,Payments!$B$5:$B$2000,A5)) -> 6250 | K5: =IF(A5="","",H5-J5) -> 6250 | L5: =IF(A5="","",SUMIFS('Time Log'!$D$5:$D$2000,'Time Log'!$B$5:$B$2000,A5)) -> 2.5 | M5: =IF(OR(A5="",L5=0),"",H5/L5) -> 5000 | N5: 1 | O5: Yes | P5: No | Q5: Yes | R5: Example row: delete or overwrite
I6: =IF(A6="","",H6*0.5) | J6: =IF(A6="","",SUMIFS(Payments!$D$5:$D$2000,Payments!$B$5:$B$2000,A6)) | K6: =IF(A6="","",H6-J6) | L6: =IF(A6="","",SUMIFS('Time Log'!$D$5:$D$2000,'Time Log'!$B$5:$B$2000,A6)) | M6: =IF(OR(A6="",L6=0),"",H6/L6)
I7: =IF(A7="","",H7*0.5) | J7: =IF(A7="","",SUMIFS(Payments!$D$5:$D$2000,Payments!$B$5:$B$2000,A7)) | K7: =IF(A7="","",H7-J7) | L7: =IF(A7="","",SUMIFS('Time Log'!$D$5:$D$2000,'Time Log'!$B$5:$B$2000,A7)) | M7: =IF(OR(A7="",L7=0),"",H7/L7)
I8: =IF(A8="","",H8*0.5) | J8: =IF(A8="","",SUMIFS(Payments!$D$5:$D$2000,Payments!$B$5:$B$2000,A8)) | K8: =IF(A8="","",H8-J8) | L8: =IF(A8="","",SUMIFS('Time Log'!$D$5:$D$2000,'Time Log'!$B$5:$B$2000,A8)) | M8: =IF(OR(A8="",L8=0),"",H8/L8)
I9: =IF(A9="","",H9*0.5) | J9: =IF(A9="","",SUMIFS(Payments!$D$5:$D$2000,Payments!$B$5:$B$2000,A9)) | K9: =IF(A9="","",H9-J9) | L9: =IF(A9="","",SUMIFS('Time Log'!$D$5:$D$2000,'Time Log'!$B$5:$B$2000,A9)) | M9: =IF(OR(A9="",L9=0),"",H9/L9)
I10: =IF(A10="","",H10*0.5) | J10: =IF(A10="","",SUMIFS(Payments!$D$5:$D$2000,Payments!$B$5:$B$2000,A10)) | K10: =IF(A10="","",H10-J10) | L10: =IF(A10="","",SUMIFS('Time Log'!$D$5:$D$2000,'Time Log'!$B$5:$B$2000,A10)) | M10: =IF(OR(A10="",L10=0),"",H10/L10)
I11: =IF(A11="","",H11*0.5) | J11: =IF(A11="","",SUMIFS(Payments!$D$5:$D$2000,Payments!$B$5:$B$2000,A11)) | K11: =IF(A11="","",H11-J11) | L11: =IF(A11="","",SUMIFS('Time Log'!$D$5:$D$2000,'Time Log'!$B$5:$B$2000,A11)) | M11: =IF(OR(A11="",L11=0),"",H11/L11)
I12: =IF(A12="","",H12*0.5) | J12: =IF(A12="","",SUMIFS(Payments!$D$5:$D$2000,Payments!$B$5:$B$2000,A12)) | K12: =IF(A12="","",H12-J12) | L12: =IF(A12="","",SUMIFS('Time Log'!$D$5:$D$2000,'Time Log'!$B$5:$B$2000,A12)) | M12: =IF(OR(A12="",L12=0),"",H12/L12)
I13: =IF(A13="","",H13*0.5) | J13: =IF(A13="","",SUMIFS(Payments!$D$5:$D$2000,Payments!$B$5:$B$2000,A13)) | K13: =IF(A13="","",H13-J13) | L13: =IF(A13="","",SUMIFS('Time Log'!$D$5:$D$2000,'Time Log'!$B$5:$B$2000,A13)) | M13: =IF(OR(A13="",L13=0),"",H13/L13)
I14: =IF(A14="","",H14*0.5) | J14: =IF(A14="","",SUMIFS(Payments!$D$5:$D$2000,Payments!$B$5:$B$2000,A14)) | K14: =IF(A14="","",H14-J14) | L14: =IF(A14="","",SUMIFS('Time Log'!$D$5:$D$2000,'Time Log'!$B$5:$B$2000,A14)) | M14: =IF(OR(A14="",L14=0),"",H14/L14)
I15: =IF(A15="","",H15*0.5) | J15: =IF(A15="","",SUMIFS(Payments!$D$5:$D$2000,Payments!$B$5:$B$2000,A15)) | K15: =IF(A15="","",H15-J15) | L15: =IF(A15="","",SUMIFS('Time Log'!$D$5:$D$2000,'Time Log'!$B$5:$B$2000,A15)) | M15: =IF(OR(A15="",L15=0),"",H15/L15)
I16: =IF(A16="","",H16*0.5) | J16: =IF(A16="","",SUMIFS(Payments!$D$5:$D$2000,Payments!$B$5:$B$2000,A16)) | K16: =IF(A16="","",H16-J16) | L16: =IF(A16="","",SUMIFS('Time Log'!$D$5:$D$2000,'Time Log'!$B$5:$B$2000,A16)) | M16: =IF(OR(A16="",L16=0),"",H16/L16)
I17: =IF(A17="","",H17*0.5) | J17: =IF(A17="","",SUMIFS(Payments!$D$5:$D$2000,Payments!$B$5:$B$2000,A17)) | K17: =IF(A17="","",H17-J17) | L17: =IF(A17="","",SUMIFS('Time Log'!$D$5:$D$2000,'Time Log'!$B$5:$B$2000,A17)) | M17: =IF(OR(A17="",L17=0),"",H17/L17)
... I154: =IF(A154="","",H154*0.5) | J154: =IF(A154="","",SUMIFS(Payments!$D$5:$D$2000,Payments!$B$5:$B$2000,A154)) | K154: =IF(A154="","",H154-J154) | L154: =IF(A154="","",SUMIFS('Time Log'!$D$5:$D$2000,'Time Log'!$B$5:$B$2000,A154)) | M154: =IF(OR(A154="",L154=0),"",H154/L154)

Sheet Time Log
A1: Time log
A2: One row per work session. Hours feed the Projects sheet.
A4: Date | B4: Project ID | C4: Task | D4: Hours
A5: 46329 | B5: P000 EXAMPLE | C5: Example: research and sketches | D5: 2.5

Sheet Payments
A1: Payments received
A2: Record every deposit and balance. The M-Pesa code is your proof of payment.
A4: Date | B4: Project ID | C4: Type | D4: Amount (KES) | E4: M-Pesa / bank code | F4: Invoice no. | G4: Receipt no.
A5: 46329 | B5: P000 EXAMPLE | C5: Deposit | D5: 6250 | E5: EXAMPLE123 | F5: INV-001 | G5: RCT-001

Sheet Clients & Data
A1: Clients and data register
A2: Data Protection Act, 2019: record what personal data you hold, why, and when to delete it.
A4: Client | B4: Phone / email | C4: Personal data held | D4: Why (lawful basis) | E4: Marketing consent? | F4: Source of lead | G4: Project end date | H4: Delete / archive by | I4: Notes
A5: Wanjiru's Bakery (EXAMPLE) | B5: example@email.com | C5: Name, phone, logo files, M-Pesa code | D5: Contract; legal duty (tax records) | E5: Yes | F5: Instagram | G5: 46338 | H5: =IF(G5="","",EDATE(G5,24)) -> 47069 | I5: Example row
H6: =IF(G6="","",EDATE(G6,24))
H7: =IF(G7="","",EDATE(G7,24))
H8: =IF(G8="","",EDATE(G8,24))
H9: =IF(G9="","",EDATE(G9,24))
H10: =IF(G10="","",EDATE(G10,24))
H11: =IF(G11="","",EDATE(G11,24))
H12: =IF(G12="","",EDATE(G12,24))
H13: =IF(G13="","",EDATE(G13,24))
H14: =IF(G14="","",EDATE(G14,24))
H15: =IF(G15="","",EDATE(G15,24))
H16: =IF(G16="","",EDATE(G16,24))
H17: =IF(G17="","",EDATE(G17,24))
... H300: =IF(G300="","",EDATE(G300,24))
A302: Delete / archive by = project end date + 24 months (assumption from the Privacy Policy; invoices and receipts are kept at least 5 years for tax, so confirm with KRA).
